pysimpletime.py
pysimpletime-2.0.0.dist-info/WHEEL
pysimpletime-2.0.0.dist-info/METADATA
pysimpletime-2.0.0.dist-info/RECORD
